tree_sitter_cuda/__init__.py
tree_sitter_cuda/__init__.pyi
tree_sitter_cuda/_binding.pyd
tree_sitter_cuda/binding.c
tree_sitter_cuda/py.typed
tree_sitter_cuda/queries/highlights.scm
tree_sitter_cuda-0.21.1.dist-info/licenses/LICENSE
tree_sitter_cuda-0.21.1.dist-info/METADATA
tree_sitter_cuda-0.21.1.dist-info/WHEEL
tree_sitter_cuda-0.21.1.dist-info/top_level.txt
tree_sitter_cuda-0.21.1.dist-info/RECORD
