Metadata-Version: 2.4
Name: tree-sitter-cuda
Version: 0.21.1
Summary: CUDA grammar for tree-sitter
Author: Stephan Seitz
License: MIT
Project-URL: Homepage, https://github.com/tree-sitter-grammars/tree-sitter-cuda
Keywords: incremental,parsing,tree-sitter,cuda
Classifier: Intended Audience :: Developers
Classifier: Topic :: Software Development :: Compilers
Classifier: Topic :: Text Processing :: Linguistic
Classifier: Typing :: Typed
Requires-Python: >=3.10
License-File: LICENSE
Provides-Extra: core
Requires-Dist: tree-sitter~=0.24; extra == "core"
Dynamic: license-file
